maxmods/__init__.py
maxmods/auth/__init__.py
maxmods/auth/auth.py
maxmods/auth/main.py
maxmods/auth/logs/__init__.py
maxmods-0.5.0.dist-info/LICENSE
maxmods-0.5.0.dist-info/METADATA
maxmods-0.5.0.dist-info/WHEEL
maxmods-0.5.0.dist-info/top_level.txt
maxmods-0.5.0.dist-info/RECORD
