Metadata-Version: 2.1
Name: maxmods
Version: 0.5.0
Summary: A collection of tools and utilities for Python. It includes modules for authentication, menus, and more. The library is released under the MIT License and the documentation is generated by an AI trained by OpenAI.
Home-page: https://github.com/maxwellewxam/maxmods/
Author: Max Colby
Author-email: maxwellipe43662@gmail.com
License: MIT
Classifier: Intended Audience :: Developers
Classifier: License :: OSI Approved :: MIT License
Classifier: Programming Language :: Python
Classifier: Programming Language :: Python :: 3
Classifier: Programming Language :: Python :: 3.6
Classifier: Programming Language :: Python :: 3.7
Classifier: Programming Language :: Python :: 3.8
Classifier: Programming Language :: Python :: 3.9
Classifier: Programming Language :: Python :: 3.10
Classifier: Programming Language :: Python :: 3.11
Classifier: Operating System :: OS Independent
License-File: LICENSE
Requires-Dist: jsonpath-ng
Requires-Dist: flask-sqlalchemy
Requires-Dist: flask
Requires-Dist: flask-restful
Requires-Dist: cryptography
Requires-Dist: keyboard
Requires-Dist: pygame
Requires-Dist: numpy
Requires-Dist: bcrypt
